apsw/__init__.cpython-312-aarch64-linux-musl.so
apsw/__init__.pyi
apsw/__main__.py
apsw/_unicode.cpython-312-aarch64-linux-musl.so
apsw/bestpractice.py
apsw/ext.py
apsw/fts5.py
apsw/fts5aux.py
apsw/fts5query.py
apsw/fts_test_strings
apsw/mcall.py
apsw/py.typed
apsw/shell.py
apsw/speedtest.py
apsw/trace.py
apsw/unicode.py
apsw/tests/__main__.py
apsw/tests/carray.py
apsw/tests/ftstests.py
apsw/tests/jsonb.py
apsw/tests/mctests.py
apsw/tests/sessiontests.py
apsw_sqlite3mc-3.51.2.0.dist-info/METADATA
apsw_sqlite3mc-3.51.2.0.dist-info/WHEEL
apsw_sqlite3mc-3.51.2.0.dist-info/entry_points.txt
apsw_sqlite3mc-3.51.2.0.dist-info/top_level.txt
apsw_sqlite3mc-3.51.2.0.dist-info/RECORD
apsw_sqlite3mc-3.51.2.0.dist-info/licenses/LICENSE
