Metadata-Version: 2.4
Name: apsw_sqlite3mc
Version: 3.51.2.0
Summary: SQLite3 Multiple Ciphers combined with Another Python SQLite Wrapper
Home-page: https://github.com/utelle/apsw-sqlite3mc
Author: Ulrich Telle
Author-email: github@telle-online.de
License: OSI Approved
Project-URL: Documentation (APSW), https://rogerbinns.github.io/apsw/
Project-URL: Documentation (MultipleCiphers), https://utelle.github.io/SQLite3MultipleCiphers/
Project-URL: Documentation (SQLite), https://sqlite.org/lang.html
Project-URL: Support/Discussions, https://github.com/utelle/apsw-sqlite3mc?tab=readme-ov-file#supportdiscussions
Project-URL: Issue Tracker, https://github.com/utelle/apsw-sqlite3mc/issues
Project-URL: Code, https://github.com/utelle/apsw-sqlite3mc
Keywords: database,sqlite,encryption
Platform: any
Classifier: Development Status :: 5 - Production/Stable
Classifier: Intended Audience :: Developers
Classifier: Programming Language :: C
Classifier: Programming Language :: Python :: 3
Classifier: Topic :: Database :: Front-Ends
Classifier: Topic :: Security :: Cryptography
Requires-Python: >=3.10
License-File: LICENSE
Dynamic: author
Dynamic: author-email
Dynamic: classifier
Dynamic: description
Dynamic: description-content-type
Dynamic: home-page
Dynamic: keywords
Dynamic: license
Dynamic: license-file
Dynamic: platform
Dynamic: project-url
Dynamic: requires-python
Dynamic: summary
